{
    "keep": {
        "days": true,
        "amount": 30
    },
    "auditLog": "logs/error/.0def03b64c299f4b685ff24e0349f2e9fd57ac6b-audit.json",
    "files": [
        {
            "date": 1730544021594,
            "name": "logs/error/error-2024-11-02.log",
            "hash": "89a51bb7158193257470b68de1d790fa37d27217ae5a55222da4dec2341109b9"
        },
        {
            "date": 1730566921565,
            "name": "logs/error/error-2024-11-03.log",
            "hash": "edc4c53952402ed9dd77cff0a121a686667eeec4f132a55df7f658211120c839"
        }
    ],
    "hashType": "sha256"
}